publish_mcp_server-0.1.3.dist-info/licenses/LICENSE
publish_mcp_server_pkg/__init__.py
publish_mcp_server_pkg/publish_mcp_server.py
publish_mcp_server_pkg/validate_schema.py
publish_mcp_server-0.1.3.dist-info/METADATA
publish_mcp_server-0.1.3.dist-info/WHEEL
publish_mcp_server-0.1.3.dist-info/entry_points.txt
publish_mcp_server-0.1.3.dist-info/top_level.txt
publish_mcp_server-0.1.3.dist-info/RECORD
