Metadata-Version: 2.4
Name: publish-mcp-server
Version: 0.1.3
Summary: An MCP server that helps users publish their MCP servers to the registry
Author-email: Marlene Mhangami <marlenemhangami@gmail.com>
License-Expression: MIT
Project-URL: Homepage, https://github.com/marlenezw/publish-mcp-server
Project-URL: Bug Tracker, https://github.com/marlenezw/publish-mcp-server/issues
Project-URL: Repository, https://github.com/marlenezw/publish-mcp-server
Keywords: mcp,model-context-protocol,server,publishing
Classifier: Development Status :: 4 - Beta
Classifier: Intended Audience :: Developers
Classifier: Programming Language :: Python :: 3
Classifier: Programming Language :: Python :: 3.8
Classifier: Programming Language :: Python :: 3.9
Classifier: Programming Language :: Python :: 3.10
Classifier: Programming Language :: Python :: 3.11
Classifier: Programming Language :: Python :: 3.12
Requires-Python: >=3.8
License-File: LICENSE
Requires-Dist: fastmcp>=0.1.0
Dynamic: license-file
